{
	"title": "my book",
	"description": "我的gitbook文档",
    "author": "zoro",
	"language": "zh-hans",
	"gitbook": "3.2.3",
	"links": {
		"sidebar": {
			"我的网站": "http://qlight.site"
		}
	},
	"plugins": [
		"-livereload",
   		"tbfed-pagefooter@^0.0.1",
		"chapter-fold",
   		"splitter@^0.0.8"
	],
	"theme-default": {
		"showLevel": true
	},
	"pluginsConfig": {
    	"tbfed-pagefooter": {
        	"copyright":"Copyright &copy www.qlight.site 2020",
        	"modify_label": "Modified at ",
        	"modify_format": "YYYY-MM-DD HH:mm:ss"
    	}
}	
}
